hi_nish/__init__.py
hi_nish/hello.py
hi_nish-0.8.0.dist-info/METADATA
hi_nish-0.8.0.dist-info/WHEEL
hi_nish-0.8.0.dist-info/entry_points.txt
hi_nish-0.8.0.dist-info/top_level.txt
hi_nish-0.8.0.dist-info/RECORD
