Metadata-Version: 2.1
Name: hi_nish
Version: 0.8.0
Summary: Default template for PDM package
Author-email: NishNovae <raecrowned@gmail.com>
License: MIT
Requires-Python: ==3.12.*
